agently_triggerflow/LICENSE
agently_triggerflow/TriggerFlow.py
agently_triggerflow/TriggerFlowChunk.py
agently_triggerflow/TriggerFlowDispatch.py
agently_triggerflow/TriggerFlowResult.py
agently_triggerflow/TriggerFlowRuntimeData.py
agently_triggerflow/__init__.py
agently_triggerflow-0.1.0rc20250207.dist-info/LICENSE
agently_triggerflow-0.1.0rc20250207.dist-info/METADATA
agently_triggerflow-0.1.0rc20250207.dist-info/WHEEL
agently_triggerflow-0.1.0rc20250207.dist-info/RECORD
